{
	"configurations" : 
	[
		{
			"directories" : 
			[
				{
					"build" : ".",
					"hasInstallRule" : true,
					"minimumCMakeVersion" : 
					{
						"string" : "3.10.2"
					},
					"projectIndex" : 0,
					"source" : ".",
					"targetIndexes" : 
					[
						0,
						1,
						2
					]
				}
			],
			"name" : "",
			"projects" : 
			[
				{
					"directoryIndexes" : 
					[
						0
					],
					"name" : "turtlebot3_project3",
					"targetIndexes" : 
					[
						0,
						1,
						2
					]
				}
			],
			"targets" : 
			[
				{
					"directoryIndex" : 0,
					"id" : "turtlebot3_drive::@6890427a1f51a3e7e1df",
					"jsonFile" : "target-turtlebot3_drive-43484b0dc0dc9cb03302.json",
					"name" : "turtlebot3_drive",
					"projectIndex" : 0
				},
				{
					"directoryIndex" : 0,
					"id" : "turtlebot3_project3_uninstall::@6890427a1f51a3e7e1df",
					"jsonFile" : "target-turtlebot3_project3_uninstall-c525903b02032184e622.json",
					"name" : "turtlebot3_project3_uninstall",
					"projectIndex" : 0
				},
				{
					"directoryIndex" : 0,
					"id" : "uninstall::@6890427a1f51a3e7e1df",
					"jsonFile" : "target-uninstall-87add3d980234c51bba9.json",
					"name" : "uninstall",
					"projectIndex" : 0
				}
			]
		}
	],
	"kind" : "codemodel",
	"paths" : 
	{
		"build" : "/home/cgcollins91/projects/ENPME661_Project03_Phase02/build/turtlebot3_project3",
		"source" : "/home/cgcollins91/projects/ENPME661_Project03_Phase02/Part02/src/turtlebot3_project3"
	},
	"version" : 
	{
		"major" : 2,
		"minor" : 0
	}
}
